drucker_dashboard/__init__.py
drucker_dashboard/_project.py
drucker_dashboard/_version.py
drucker_dashboard/app.py
drucker_dashboard/drucker_dashboard_client.py
drucker_dashboard/server.py
drucker_dashboard/apis/__init__.py
drucker_dashboard/apis/api_admin.py
drucker_dashboard/apis/api_application.py
drucker_dashboard/apis/api_evaluation.py
drucker_dashboard/apis/api_kubernetes.py
drucker_dashboard/apis/api_misc.py
drucker_dashboard/apis/api_model.py
drucker_dashboard/apis/api_service.py
drucker_dashboard/apis/common.py
drucker_dashboard/auth/__init__.py
drucker_dashboard/auth/authenticator.py
drucker_dashboard/auth/exceptions.py
drucker_dashboard/auth/ldap.py
drucker_dashboard/logger/__init__.py
drucker_dashboard/logger/logger_fluent.py
drucker_dashboard/logger/logger_interface.py
drucker_dashboard/logger/logger_jsonlogger.py
drucker_dashboard/models/__init__.py
drucker_dashboard/models/application.py
drucker_dashboard/models/application_user_role.py
drucker_dashboard/models/dao.py
drucker_dashboard/models/evaluation.py
drucker_dashboard/models/evaluation_result.py
drucker_dashboard/models/kubernetes.py
drucker_dashboard/models/model.py
drucker_dashboard/models/service.py
drucker_dashboard/models/user.py
drucker_dashboard/protobuf/__init__.py
drucker_dashboard/protobuf/drucker_pb2.py
drucker_dashboard/protobuf/drucker_pb2_grpc.py
drucker_dashboard/static/dist/index.html
drucker_dashboard/static/dist/js/bundle.js
drucker_dashboard/utils/__init__.py
drucker_dashboard/utils/hash_util.py
drucker_dashboard/utils/protobuf_util.py
drucker_dashboard-0.4.5.dist-info/LICENSE
drucker_dashboard-0.4.5.dist-info/METADATA
drucker_dashboard-0.4.5.dist-info/WHEEL
drucker_dashboard-0.4.5.dist-info/entry_points.txt
drucker_dashboard-0.4.5.dist-info/top_level.txt
drucker_dashboard-0.4.5.dist-info/RECORD
