Metadata-Version: 2.1
Name: drucker-dashboard
Version: 0.4.5
Summary: A WebUI for managing machine learning services of Rekcurd.
Home-page: https://github.com/rekcurd/drucker-dashboard
Author: Drucker team and contributors
Author-email: UNKNOWN
License: Apache License Version 2.0
Keywords: Drucker,Rekcurd,Kubernetes,Python,gRPC,Restful
Platform: UNKNOWN
Classifier: Development Status :: 3 - Alpha
Classifier: Environment :: Web Environment
Classifier: Topic :: Software Development :: Libraries :: Application Frameworks
Classifier: Intended Audience :: Developers
Classifier: Intended Audience :: Information Technology
Classifier: License :: OSI Approved :: Apache Software License
Classifier: Operating System :: OS Independent
Classifier: Programming Language :: Python
Classifier: Programming Language :: Python :: 3
Classifier: Programming Language :: Python :: 3.6
Classifier: Programming Language :: Python :: 3.7
Requires-Dist: Flask (>=1.0.2)
Requires-Dist: Flask-Cors (>=3.0.4)
Requires-Dist: grpcio (>=1.13.0)
Requires-Dist: grpcio-tools (>=1.13.0)
Requires-Dist: python-json-logger (>=0.1.9)
Requires-Dist: fluent-logger (>=0.9.3)
Requires-Dist: PyYAML (>=3.12)
Requires-Dist: SQLAlchemy (>=1.2.7)
Requires-Dist: PyMySQL (>=0.8.0)
Requires-Dist: flask-sqlalchemy (>=2.3.2)
Requires-Dist: kubernetes (>=v8.0.0)
Requires-Dist: flask-restplus (>=0.11.0)
Requires-Dist: Flask-Testing (>=0.7.1)
Requires-Dist: Flask-JWT-Simple (>=0.0.3)
Requires-Dist: python-ldap (>=3.1.0)
Requires-Dist: Flask-Migrate (>=2.2.1)
Requires-Dist: Flask-Script (>=2.0.6)
Requires-Dist: protobuf3-to-dict (>=0.1.5)
